gradus/__init__.py
gradus/ecs.py
gradus/local_handler.py
gradus_platform-0.1.1.dist-info/licenses/LICENSE
gradus_platform-0.1.1.dist-info/METADATA
gradus_platform-0.1.1.dist-info/WHEEL
gradus_platform-0.1.1.dist-info/top_level.txt
gradus_platform-0.1.1.dist-info/RECORD
