Metadata-Version: 2.4
Name: gradus-platform
Version: 0.1.1
Summary: Ferramentas Gradus
Author: William Nagano
License: Proprietary
Project-URL: Homepage, https://www.gradusconsultoria.com.br/
Keywords: aws,s3,ecs,callback,gradus
Classifier: Programming Language :: Python :: 3
Classifier: License :: Other/Proprietary License
Classifier: Operating System :: OS Independent
Requires-Python: >=3.9
License-File: LICENSE
Requires-Dist: boto3
Requires-Dist: requests
Dynamic: license-file
